[
  {
    "id": "4hWS9ZKbgfw8QK3FeCf6",
    "impostosRetidos": 0,
    "numeroNF": "040826",
    "dataEmissao": "2026-04-13",
    "percentualComissao": 0,
    "banco": "INTER",
    "statusPagamento": "Pendente",
    "valorLiquido": 160,
    "comissao": 0,
    "serviceOrderId": "26281",
    "desconto": 0,
    "valorBruto": 160,
    "orcamentoId": "OCW041426",
    "statusComissao": "Pendente",
    "clienteId": "0009",
    "formaPagamento": "À vista",
    "valorPendente": 0
  },
  {
    "id": "A4ousyOgcKWiFKhBar8N",
    "orcamentoId": "OCW045026",
    "valorBruto": 1800,
    "serviceOrderId": "26293",
    "desconto": 0,
    "formaPagamento": "BOLETO 15 DIAS",
    "valorPendente": 0,
    "clienteId": "0048",
    "statusComissao": "Pendente",
    "impostosRetidos": 90,
    "numeroNF": "270",
    "comissao": 0,
    "dataEmissao": "2026-04-23",
    "valorLiquido": 1710,
    "banco": "INTER",
    "statusPagamento": "Pendente",
    "percentualComissao": 0
  },
  {
    "id": "EhEeHTuzcXjq63y7psBs",
    "statusComissao": "Pendente",
    "clienteId": "0053",
    "valorPendente": 0,
    "formaPagamento": "BOLETO 15 DIAS",
    "desconto": 0,
    "serviceOrderId": "26301",
    "valorBruto": 180,
    "orcamentoId": "OCW045926",
    "percentualComissao": 0,
    "valorLiquido": 180,
    "statusPagamento": "Pendente",
    "banco": "INTER",
    "dataEmissao": "2026-04-23",
    "comissao": 0,
    "numeroNF": "045926",
    "impostosRetidos": 0
  },
  {
    "id": "GHL0RdL3QIb4Y39PVezp",
    "percentualComissao": 0,
    "banco": "SANTANDER",
    "statusPagamento": "Pendente",
    "valorLiquido": 9405,
    "dataEmissao": "2026-04-16",
    "comissao": 0,
    "numeroNF": "253",
    "impostosRetidos": 495,
    "statusComissao": "Pendente",
    "clienteId": "0019",
    "valorPendente": 0,
    "formaPagamento": "DEPÓSITO EM CONTA 30 DIAS",
    "serviceOrderId": "26288",
    "desconto": 0,
    "valorBruto": 9900,
    "orcamentoId": "OCW044126"
  },
  {
    "id": "GoTaEF3rhQvb900eynJn",
    "numeroNF": "045826",
    "impostosRetidos": 0,
    "comissao": 0,
    "valorLiquido": 80,
    "statusPagamento": "Pendente",
    "banco": "INTER",
    "percentualComissao": 0,
    "dataEmissao": "2026-04-23",
    "orcamentoId": "OCW045826",
    "valorBruto": 80,
    "desconto": 0,
    "serviceOrderId": "26300",
    "valorPendente": 0,
    "formaPagamento": "BOLETO 15 DIAS",
    "clienteId": "0053",
    "statusComissao": "Pendente"
  },
  {
    "id": "HH7t0gLWlK3Gv3GLZ7v0",
    "formaPagamento": "BOLETO 15 DIAS",
    "valorPendente": 0,
    "clienteId": "0021",
    "statusComissao": "Pendente",
    "orcamentoId": "OCW042826",
    "valorBruto": 450,
    "desconto": 0,
    "serviceOrderId": "26286",
    "percentualImposto": 5,
    "comissao": 0,
    "dataEmissao": "2026-04-17",
    "valorLiquido": 450,
    "banco": "Inter",
    "statusPagamento": "Pendente",
    "percentualComissao": 0,
    "impostosRetidos": 0,
    "numeroNF": "255"
  },
  {
    "id": "JMNIlDHLunHav2vXPiRQ",
    "clienteId": "0051",
    "statusComissao": "Pendente",
    "formaPagamento": "Boleto Bancário 5 dias",
    "valorPendente": 0,
    "valorBruto": 960,
    "serviceOrderId": "26296",
    "desconto": 0,
    "orcamentoId": "OCW045526",
    "dataEmissao": "2026-04-24",
    "valorLiquido": 912,
    "statusPagamento": "Pendente",
    "banco": "INTER",
    "percentualComissao": 0,
    "comissao": 0,
    "impostosRetidos": 48,
    "numeroNF": "266"
  },
  {
    "id": "MMHrhgp60QVCW7omRpAO",
    "desconto": 0,
    "serviceOrderId": "26298",
    "valorBruto": 2040,
    "orcamentoId": "OCW045226",
    "statusComissao": "Pendente",
    "clienteId": "0050",
    "valorPendente": 0,
    "formaPagamento": "CARTÃO PARCELADO",
    "numeroNF": "045226",
    "impostosRetidos": 0,
    "percentualComissao": 0,
    "valorLiquido": 2040,
    "banco": "",
    "statusPagamento": "Pendente",
    "dataEmissao": "2026-04-22",
    "comissao": 0,
    "percentualImposto": 5
  },
  {
    "id": "SxxcQ7h3qMxKdQkyxNgk",
    "statusComissao": "Pendente",
    "clienteId": "0050",
    "formaPagamento": "CARTÃO PARCELADO",
    "valorPendente": 0,
    "desconto": 0,
    "serviceOrderId": "26308",
    "valorBruto": 480,
    "orcamentoId": "OCW047226",
    "dataEmissao": "2026-04-17",
    "percentualComissao": 0,
    "valorLiquido": 480,
    "banco": "",
    "statusPagamento": "Pendente",
    "percentualImposto": 5,
    "comissao": 0,
    "impostosRetidos": 0,
    "numeroNF": "047226"
  },
  {
    "id": "TkVJUxi28dY72cvwghkt",
    "valorBruto": 320,
    "serviceOrderId": "26285",
    "desconto": 0,
    "orcamentoId": "OCW042326",
    "clienteId": "0013",
    "statusComissao": "Pendente",
    "valorPendente": 0,
    "formaPagamento": "DEPÓSITO EM CONTA 60 DIAS",
    "numeroNF": "257",
    "impostosRetidos": 16,
    "valorLiquido": 304,
    "statusPagamento": "Pendente",
    "banco": "CEF",
    "percentualComissao": 0,
    "dataEmissao": "2026-04-17",
    "comissao": 0,
    "percentualImposto": 0
  },
  {
    "id": "Vshe3itJ92QJQEjpj5Ph",
    "desconto": 0,
    "serviceOrderId": "26302",
    "valorBruto": 1900,
    "orcamentoId": "OCW046026",
    "statusComissao": "Pendente",
    "clienteId": "0053",
    "valorPendente": 0,
    "formaPagamento": "BOLETO 15 DIAS",
    "numeroNF": "046026",
    "impostosRetidos": 0,
    "percentualComissao": 0,
    "valorLiquido": 1900,
    "statusPagamento": "Pendente",
    "banco": "INTER",
    "dataEmissao": "2026-04-23",
    "comissao": 0
  },
  {
    "id": "a47xAktvATCWrBqMuITt",
    "valorPendente": 0,
    "formaPagamento": "Depósito em conta 15 Dias",
    "statusComissao": "Pendente",
    "clienteId": "0025",
    "orcamentoId": "OCW043226",
    "serviceOrderId": "26287",
    "desconto": 0,
    "valorBruto": 534,
    "comissao": 0,
    "percentualImposto": 0,
    "percentualComissao": 0,
    "valorLiquido": 507.3,
    "banco": "CEF",
    "statusPagamento": "Pendente",
    "dataEmissao": "2026-04-23",
    "numeroNF": "271",
    "impostosRetidos": 26.7
  },
  {
    "id": "diXCGB1sLwBGLeNdIDL0",
    "impostosRetidos": 46,
    "numeroNF": "251",
    "percentualImposto": 0,
    "comissao": 0,
    "dataEmissao": "2026-04-16",
    "percentualComissao": 0,
    "statusPagamento": "Pendente",
    "banco": "CEF",
    "valorLiquido": 874,
    "orcamentoId": "OCW041626",
    "desconto": 0,
    "serviceOrderId": "26282",
    "valorBruto": 920,
    "formaPagamento": "DEPÓSITO EM CONTA 30 DIAS",
    "valorPendente": 0,
    "statusComissao": "Pendente",
    "clienteId": "0011"
  },
  {
    "id": "nnbxFBm6U7tpuUiQvcT6",
    "valorBruto": 975,
    "serviceOrderId": "26299",
    "desconto": 0,
    "orcamentoId": "OCW045726",
    "clienteId": "0053",
    "statusComissao": "Pendente",
    "formaPagamento": "BOLETO 15 DIAS",
    "valorPendente": 0,
    "impostosRetidos": 0,
    "numeroNF": "045726",
    "dataEmissao": "2026-04-23",
    "valorLiquido": 975,
    "statusPagamento": "Pendente",
    "banco": "INTER",
    "percentualComissao": 0,
    "percentualImposto": 0,
    "comissao": 0
  }
]